acmeow/__init__.py
acmeow/client.py
acmeow/convenience.py
acmeow/enums.py
acmeow/exceptions.py
acmeow/orders.py
acmeow/py.typed
acmeow/_internal/__init__.py
acmeow/_internal/crypto.py
acmeow/_internal/dns.py
acmeow/_internal/encoding.py
acmeow/_internal/hooks.py
acmeow/_internal/http.py
acmeow/_internal/rate_limiter.py
acmeow/dns/__init__.py
acmeow/dns/base.py
acmeow/dns/cloudflare.py
acmeow/dns/digitalocean.py
acmeow/dns/handler.py
acmeow/dns/manual.py
acmeow/dns/route53.py
acmeow/handlers/__init__.py
acmeow/handlers/base.py
acmeow/handlers/dns.py
acmeow/handlers/http.py
acmeow/handlers/tls_alpn.py
acmeow/models/__init__.py
acmeow/models/account.py
acmeow/models/authorization.py
acmeow/models/challenge.py
acmeow/models/identifier.py
acmeow/models/order.py
acmeow-1.0.2.dist-info/METADATA
acmeow-1.0.2.dist-info/WHEEL
acmeow-1.0.2.dist-info/licenses/LICENSE
acmeow-1.0.2.dist-info/RECORD
