Metadata-Version: 2.4
Name: acmeow
Version: 1.0.2
Summary: Production-grade ACME protocol client library for automated SSL/TLS certificate management
Project-URL: Homepage, https://github.com/miichoow/ACMEOW
Project-URL: Documentation, https://miichoow.github.io/ACMEOW/
Project-URL: Repository, https://github.com/miichoow/ACMEOW
Project-URL: Issues, https://github.com/miichoow/ACMEOW/issues
Author: ACMEOW Contributors
License-Expression: Apache-2.0
License-File: LICENSE
Keywords: acme,automation,certificate,cloudflare,dns,letsencrypt,route53,ssl,tls
Classifier: Development Status :: 5 - Production/Stable
Classifier: Intended Audience :: Developers
Classifier: Intended Audience :: System Administrators
Classifier: License :: OSI Approved :: Apache Software License
Classifier: Operating System :: OS Independent
Classifier: Programming Language :: Python :: 3
Classifier: Programming Language :: Python :: 3.10
Classifier: Programming Language :: Python :: 3.11
Classifier: Programming Language :: Python :: 3.12
Classifier: Programming Language :: Python :: 3.13
Classifier: Topic :: Internet :: WWW/HTTP
Classifier: Topic :: Security :: Cryptography
Classifier: Topic :: System :: Systems Administration
Classifier: Typing :: Typed
Requires-Python: >=3.10
Requires-Dist: cryptography>=41.0.0
Requires-Dist: requests>=2.31.0
Provides-Extra: all
Requires-Dist: boto3>=1.26.0; extra == 'all'
Provides-Extra: dev
Requires-Dist: boto3-stubs[route53]>=1.26.0; extra == 'dev'
Requires-Dist: mypy>=1.0.0; extra == 'dev'
Requires-Dist: pytest-cov>=4.0.0; extra == 'dev'
Requires-Dist: pytest>=7.0.0; extra == 'dev'
Requires-Dist: ruff>=0.1.0; extra == 'dev'
Requires-Dist: types-requests>=2.31.0; extra == 'dev'
Provides-Extra: dns-route53
Requires-Dist: boto3>=1.26.0; extra == 'dns-route53'
Provides-Extra: docs
Requires-Dist: furo>=2024.1.0; extra == 'docs'
Requires-Dist: myst-parser>=3.0.0; extra == 'docs'
Requires-Dist: sphinx-autodoc-typehints>=2.0.0; extra == 'docs'
Requires-Dist: sphinx>=7.0.0; extra == 'docs'
